flask_api/__init__.py
flask_api/app.py
flask_api/compat.py
flask_api/decorators.py
flask_api/exceptions.py
flask_api/mediatypes.py
flask_api/negotiation.py
flask_api/parsers.py
flask_api/renderers.py
flask_api/request.py
flask_api/response.py
flask_api/settings.py
flask_api/status.py
flask_api/__pycache__/__init__.cpython-39.pyc
flask_api/__pycache__/app.cpython-39.pyc
flask_api/__pycache__/compat.cpython-39.pyc
flask_api/__pycache__/exceptions.cpython-39.pyc
flask_api/__pycache__/mediatypes.cpython-39.pyc
flask_api/__pycache__/negotiation.cpython-39.pyc
flask_api/__pycache__/parsers.cpython-39.pyc
flask_api/__pycache__/renderers.cpython-39.pyc
flask_api/__pycache__/request.cpython-39.pyc
flask_api/__pycache__/response.cpython-39.pyc
flask_api/__pycache__/settings.cpython-39.pyc
flask_api/__pycache__/status.cpython-39.pyc
flask_api/static/css/bootstrap-tweaks.css
flask_api/static/css/bootstrap.min.css
flask_api/static/css/default.css
flask_api/static/css/prettify.css
flask_api/static/img/glyphicons-halflings-white.png
flask_api/static/img/glyphicons-halflings.png
flask_api/static/img/grid.png
flask_api/static/js/bootstrap.min.js
flask_api/static/js/default.js
flask_api/static/js/jquery-1.8.1-min.js
flask_api/static/js/prettify-min.js
flask_api/templates/base.html
flask_api/tests/__init__.py
flask_api/tests/test_app.py
flask_api/tests/test_exceptions.py
flask_api/tests/test_mediatypes.py
flask_api/tests/test_negotiation.py
flask_api/tests/test_parsers.py
flask_api/tests/test_renderers.py
flask_api/tests/test_request.py
flask_api/tests/test_settings.py
flask_api/tests/test_status.py
Flask_API-3.1.dist-info/LICENSE.md
Flask_API-3.1.dist-info/METADATA
Flask_API-3.1.dist-info/WHEEL
Flask_API-3.1.dist-info/top_level.txt
Flask_API-3.1.dist-info/RECORD
